fpcs-1.0.0.dist-info/RECORD
fpcs-1.0.0.dist-info/WHEEL
fpcs-1.0.0.dist-info/top_level.txt
fpcs-1.0.0.dist-info/METADATA
fpcs-1.0.0.dist-info/licenses/LICENSE
fpcs/fpcs_cy.pyx
fpcs/fpcs_cy.c
fpcs/__init__.py
fpcs/fpcs_pure.py
fpcs/fpcs_cy.cpython-314-darwin.so
