Metadata-Version: 2.4
Name: fpcs
Version: 1.0.0
Summary: Feature-Preserving Compensated Sampling for time series downsampling
Author-email: Thomas Michelat <thomas.michelat@gmail.com>
License-Expression: MIT
Project-URL: Homepage, https://github.com/tmichela/fpcs
Project-URL: Repository, https://github.com/tmichela/fpcs
Keywords: downsampling,time series,visualization,data science
Classifier: Intended Audience :: Developers
Classifier: Intended Audience :: Science/Research
Classifier: Operating System :: OS Independent
Classifier: Programming Language :: Python :: 3
Classifier: Programming Language :: Cython
Classifier: Topic :: Scientific/Engineering :: Information Analysis
Classifier: Topic :: Scientific/Engineering :: Physics
Classifier: Topic :: Scientific/Engineering :: Visualization
Requires-Python: >=3.11
License-File: LICENSE
Requires-Dist: numpy
Provides-Extra: dev
Requires-Dist: cython; extra == "dev"
Requires-Dist: matplotlib; extra == "dev"
Requires-Dist: lttbc; extra == "dev"
Requires-Dist: pytest; extra == "dev"
Requires-Dist: pytest-benchmark; extra == "dev"
Dynamic: license-file
